markdown_github/__init__.py
markdown_github/headerid.py
markdown_github/magiclink.py
markdown_github/superfences.py
wirecloud_markdown_github-1.2.dist-info/METADATA
wirecloud_markdown_github-1.2.dist-info/RECORD
wirecloud_markdown_github-1.2.dist-info/WHEEL
wirecloud_markdown_github-1.2.dist-info/top_level.txt
