Metadata-Version: 2.1
Name: wirecloud-markdown-github
Version: 1.2
Summary: Set of markdown extensions for getting similar behaviour to GFM.
Home-page: https://github.com/conwetlab/markdown_github
Author: CoNWeT Lab
Author-email: wirecloud@conwet.com
License: UNKNOWN
Platform: UNKNOWN
Classifier: Development Status :: 4 - Beta
Classifier: Operating System :: OS Independent
Classifier: License :: OSI Approved :: BSD License
Classifier: Intended Audience :: Developers
Classifier: Environment :: Web Environment
Classifier: Programming Language :: Python
Classifier: Topic :: Text Processing :: Filters
Classifier: Topic :: Text Processing :: Markup :: HTML
Requires-Dist: markdown (>=3.0)
Requires-Dist: pymdown-extensions
